{
  "zabbix_export": {
    "date": "2022-10-04T07:40:34Z",
    "groups": [
      {
        "name": "Templates/Network devices",
        "uuid": "36bff6c29af64692839d077febfc7079"
      }
    ],
    "templates": [
      {
        "description": "Template SNMP Moxa iks6726a made by automate@izi-it\nHash: xxxxxxxxxxxxxxx\n\n.",
        "groups": [
          {
            "name": "Templates/Network devices"
          }
        ],
        "name": "SNMP Moxa iks6726a",
        "tags": [
          {
            "tag": "layer",
            "value": "network"
          },
          {
            "tag": "provider",
            "value": "izi-it"
          },
          {
            "tag": "vendor",
            "value": "Moxa iks6726a"
          }
        ],
        "template": "SNMP Moxa iks6726a",
        "templates": [
          {
            "name": "SNMP Moxa iks6726a cpu"
          },
          {
            "name": "SNMP Moxa iks6726a memory"
          }
        ],
        "uuid": "b5c4c6c085ae40068261a68c932de5ce"
      }
    ],
    "version": "6.0"
  }
}